[
  {
    "color": "text-red-800",
    "desc": "Meningkatkan pelayanan yang maksimal kepada masyarakat desa dan daya saing desa."
  },
  {
    "color": "text-blue-400",
    "desc": "Meningkatkan konektivitas digital untuk mendukung pertumbuhan ekonomi dan pendidikan."
  },
  {
    "color": "text-blue-800",
    "desc": "Mengembangkan infrastruktur yang memfasilitasi pertumbuhan desa."
  },
  {
    "color": "text-yellow-600",
    "desc": " Mewujudkan dan meningkatkan serta meneruskan tata kelola pemerintahan desa yang lebih baik."
  }
]